LICENSE
README.md
pyproject.toml
requirements.txt
pyzag/__init__.py
pyzag/chunktime.py
pyzag/nonlinear.py
pyzag/ode.py
pyzag/reparametrization.py
pyzag/stochastic.py
pyzag.egg-info/PKG-INFO
pyzag.egg-info/SOURCES.txt
pyzag.egg-info/dependency_links.txt
pyzag.egg-info/requires.txt
pyzag.egg-info/top_level.txt
test/test_adjoint.py
test/test_chunktime.py
test/test_initial_conditions.py
test/test_ode.py
test/test_predictors.py
test/test_reparametrization.py
test/test_steppers.py