Metadata-Version: 2.4
Name: pyzag
Version: 1.1.1
Summary: A Python package for efficiently solving and taking derivatives of systems of recursive nonlinear equations
Author-email: Mark Messner <messner@anl.gov>
Project-URL: Homepage, https://github.com/applied-material-modeling/pyzag
Project-URL: Issues, https://github.com/applied-material-modeling/pyzag/issues
Classifier: Programming Language :: Python :: 3
Classifier: License :: OSI Approved :: MIT License
Classifier: Operating System :: OS Independent
Requires-Python: >=3.8
License-File: LICENSE
Requires-Dist: torch
Requires-Dist: tqdm
Requires-Dist: numpy<2
Requires-Dist: matplotlib
Requires-Dist: pyro-ppl
Requires-Dist: scipy
Dynamic: license-file
